virtuered_webui/__init__.py
virtuered_webui/cli.py
virtuered_webui/server.py
virtuered_webui/frontend/404.html
virtuered_webui/frontend/config.js
virtuered_webui/frontend/dashboard.html
virtuered_webui/frontend/dashboard.txt
virtuered_webui/frontend/favicon.ico
virtuered_webui/frontend/file.svg
virtuered_webui/frontend/globe.svg
virtuered_webui/frontend/index.html
virtuered_webui/frontend/index.txt
virtuered_webui/frontend/models.html
virtuered_webui/frontend/models.txt
virtuered_webui/frontend/next.svg
virtuered_webui/frontend/progress.html
virtuered_webui/frontend/progress.txt
virtuered_webui/frontend/runs.html
virtuered_webui/frontend/runs.txt
virtuered_webui/frontend/vercel.svg
virtuered_webui/frontend/window.svg
virtuered_webui/frontend/_next/static/chunks/201-5e61904a6737a442.js
virtuered_webui/frontend/_next/static/chunks/4bd1b696-9094e013355a9834.js
virtuered_webui/frontend/_next/static/chunks/508-216c62365afa40b3.js
virtuered_webui/frontend/_next/static/chunks/629.f0b62c69ed7322f7.js
virtuered_webui/frontend/_next/static/chunks/643-70fd7e44c0d42067.js
virtuered_webui/frontend/_next/static/chunks/684-946d9d1fa989fb11.js
virtuered_webui/frontend/_next/static/chunks/766-ea43befa0d36139b.js
virtuered_webui/frontend/_next/static/chunks/808-77fde702519eae9c.js
virtuered_webui/frontend/_next/static/chunks/817-f84cf30f3da842df.js
virtuered_webui/frontend/_next/static/chunks/874-51f7136ed064388a.js
virtuered_webui/frontend/_next/static/chunks/8e1d74a4-652f6b40d1652731.js
virtuered_webui/frontend/_next/static/chunks/904-ed9e360c234fb195.js
virtuered_webui/frontend/_next/static/chunks/966-f53b5ea58466e920.js
virtuered_webui/frontend/_next/static/chunks/9c4e2130-72e6352738e0319a.js
virtuered_webui/frontend/_next/static/chunks/framework-fe62ec11f289b4d6.js
virtuered_webui/frontend/_next/static/chunks/main-app-38177f588b9b2e48.js
virtuered_webui/frontend/_next/static/chunks/main-d49d6f3056f140fb.js
virtuered_webui-0.1.1.dist-info/licenses/LICENSE
virtuered_webui-0.1.1.dist-info/METADATA
virtuered_webui-0.1.1.dist-info/WHEEL
virtuered_webui-0.1.1.dist-info/entry_points.txt
virtuered_webui-0.1.1.dist-info/top_level.txt
virtuered_webui-0.1.1.dist-info/RECORD
