Metadata-Version: 2.4
Name: virtuered-webui
Version: 0.1.1
Summary: VirtueRed Web UI packaged with Python CLI
Home-page: https://github.com/your-org/virtuered-webui
Author: Yijia Zheng
Author-email: yijiazheng17@gmail.com
Classifier: Programming Language :: Python :: 3
Classifier: License :: OSI Approved :: MIT License
Classifier: Operating System :: OS Independent
Requires-Python: >=3.7
License-File: LICENSE
Requires-Dist: fastapi
Requires-Dist: uvicorn
Requires-Dist: click
Requires-Dist: pyfiglet
Requires-Dist: rich
Dynamic: author
Dynamic: author-email
Dynamic: classifier
Dynamic: description
Dynamic: description-content-type
Dynamic: home-page
Dynamic: license-file
Dynamic: requires-dist
Dynamic: requires-python
Dynamic: summary
